minimal_pba_cli/__init__.py
minimal_pba_cli/cli.py
minimal_pba_cli/customization.py
minimal_pba_cli/plugin.py
minimal_pba_cli/upgrade.py
minimal_pba_cli/util.py
minimal_pba_cli-0.0.5.dist-info/METADATA
minimal_pba_cli-0.0.5.dist-info/WHEEL
minimal_pba_cli-0.0.5.dist-info/entry_points.txt
minimal_pba_cli-0.0.5.dist-info/top_level.txt
minimal_pba_cli-0.0.5.dist-info/RECORD
